{
  "kind": "collectionType",
  "collectionName": "estudiantes",
  "info": {
    "singularName": "estudiante",
    "pluralName": "estudiantes",
    "displayName": "Estudiante",
    "description": "Persona que se matricula en módulos"
  },
  "options": {
    "draftAndPublish": false
  },
  "attributes": {
    "dni": {
      "type": "string",
      "required": true,
      "unique": true
    },
    "nombres": {
      "type": "string",
      "required": true
    },
    "apellidos": {
      "type": "string",
      "required": true
    },
    "email": {
      "type": "email",
      "unique": true
    },
    "telefono": {
      "type": "string"
    },
    "fechaNacimiento": {
      "type": "date"
    }
  }
}
